html_json_forms/__init__.py
html_json_forms/serializers.py
html_json_forms/utils.py
html_json_forms-1.1.1.dist-info/LICENSE
html_json_forms-1.1.1.dist-info/METADATA
html_json_forms-1.1.1.dist-info/WHEEL
html_json_forms-1.1.1.dist-info/top_level.txt
html_json_forms-1.1.1.dist-info/RECORD
